README
setup.cfg
setup.py
pyMomentum/__init__.py
pyMomentum.egg-info/PKG-INFO
pyMomentum.egg-info/SOURCES.txt
pyMomentum.egg-info/dependency_links.txt
pyMomentum.egg-info/not-zip-safe
pyMomentum.egg-info/requires.txt
pyMomentum.egg-info/top_level.txt
pyMomentum/sms/__init__.py
pyMomentum/sms/sms.py
pyMomentum/sms/providers/__init__.py
pyMomentum/sms/providers/mutlucell.py
pyMomentum/sms/providers/providers.py
pyMomentum/sms/providers/sanalsantral.py