Metadata-Version: 1.0
Name: pyMomentum
Version: 0.1.4
Summary: Python libraries developed by Momentum
Home-page: https://github.com/MomentumAS/pyMomentum
Author: Momentum Teknoloji AS
Author-email: info@mtas.com.tr
License: MIT
Keywords: momentum,library,sms
Platform: UNKNOWN
